{
  "last_updated": "2026-05-24T08:35:42.440867",
  "total_routes": 177,
  "active_vehicles": 25,
  "status": "active",
  "routes_by_type": {},
  "active_alerts": [
    {
      "id": "1010008",
      "title": "",
      "description": null,
      "severity": 1,
      "route_id": "unknown"
    },
    {
      "id": "1011603",
      "title": "",
      "description": null,
      "severity": 3,
      "route_id": "unknown"
    },
    {
      "id": "1001814",
      "title": "",
      "description": "Please see station personnel or use a station call box to request assistance.",
      "severity": 1,
      "route_id": "unknown"
    },
    {
      "id": "1002245",
      "title": "",
      "description": null,
      "severity": 3,
      "route_id": "unknown"
    },
    {
      "id": "1002887",
      "title": "",
      "description": null,
      "severity": 8,
      "route_id": "unknown"
    },
    {
      "id": "1010879",
      "title": "",
      "description": null,
      "severity": 1,
      "route_id": "unknown"
    },
    {
      "id": "1002889",
      "title": "",
      "description": null,
      "severity": 8,
      "route_id": "unknown"
    },
    {
      "id": "1001858",
      "title": "",
      "description": "Skipped outbound stops:\r\nTremont St opp St Mary's High School\r\nMarket St @ Tremont St",
      "severity": 7,
      "route_id": "unknown"
    },
    {
      "id": "1009804",
      "title": "",
      "description": null,
      "severity": 3,
      "route_id": "unknown"
    },
    {
      "id": "1011974",
      "title": "",
      "description": null,
      "severity": 3,
      "route_id": "unknown"
    },
    {
      "id": "1010071",
      "title": "",
      "description": null,
      "severity": 1,
      "route_id": "unknown"
    },
    {
      "id": "1009001",
      "title": "",
      "description": null,
      "severity": 3,
      "route_id": "unknown"
    },
    {
      "id": "1011899",
      "title": "",
      "description": "Affected stops:\r\nSurface Rd @ Hanover St (outbound)\r\nDevonshire St @ Milk St (outbound)\r\nPearl St @ Congress St (outbound)\r\nCongress St @ State St (outbound)\r\nCongress St @ North St (outbound)\r\nDevonshire St @ Water St (inbound)\r\nBroadway @ Lincoln St (inbound)\r\nDevonshire St @ Milk St (inbound)\r\nBroadway @ Mt Vernon St (inbound)\r\nSullivan Square (inbound)\r\nSullivan Square (inbound)\r\nMain St opp Schraffts Bldg (inbound)\r\nBunker Hill St @ Main St (inbound)\r\nBunker Hill St @ Baldwin St (inbound)\r\nBunker Hill St @ Auburn St (inbound)\r\nBunker Hill St @ Clarken Ct (inbound)\r\nBunker Hill St @ Sullivan St (inbound)\r\nBunker Hill St @ Green St (inbound)\r\nBunker Hill St @ Concord St (inbound)\r\nBunker Hill St @ Ferrin St (inbound)\r\nBunker Hill St @ Vine St (inbound)\r\nBunker Hill St @ Lowney Way (inbound)\r\nAdams St @ Lowney Way (inbound)\r\nPark St @ Warren St (inbound)\r\nMain St @ City Sq (inbound)\r\nN Washington St @ Medford St (inbound)\r\nSurface Rd @ Hanover St (inbound)",
      "severity": 1,
      "route_id": "unknown"
    },
    {
      "id": "1002019",
      "title": "",
      "description": "This is to accommodate track improvement work and the replacement of 14,000 railroad ties and is scheduled to complete mid-May, 2026.\r\n\r\nSingle-track operations will be in effect throughout this period so boarding areas may change.\r\n\r\nTemporarily Suspended Inbound Trains:\r\n\u2022\t126 (8:49am from Newburyport)\r\n\u2022\t1132 (10:53am from Beverly)\r\n\u2022\t46 (1:47pm from Rockport)\r\n\u2022\t1150 (3:23 from Beverly)\r\n\r\nTemporarily Suspended Outbound Trains:\r\n\u2022\t125 (8:35am to Newburyport)\r\n\u2022\t1129 (9:35am to Beverly)\r\n\u2022\t39 (12:05pm to Rockport)\r\n\u2022\t11:47am (2:05pm to Beverly)\r\n\r\n\r\n",
      "severity": 8,
      "route_id": "unknown"
    },
    {
      "id": "1001861",
      "title": "",
      "description": "Please see station personnel or use a station call box to request assistance.",
      "severity": 1,
      "route_id": "unknown"
    },
    {
      "id": "1001813",
      "title": "",
      "description": "Affected routes:\r\n426\r\n429\r\n435\r\n441\r\n442\r\n455",
      "severity": 1,
      "route_id": "unknown"
    },
    {
      "id": "1002246",
      "title": "",
      "description": null,
      "severity": 3,
      "route_id": "unknown"
    },
    {
      "id": "1001819",
      "title": "",
      "description": null,
      "severity": 1,
      "route_id": "unknown"
    },
    {
      "id": "1000002",
      "title": "",
      "description": "There are accessible mini-high platforms at the Western end of both the Track 1 and Track 2 sides. However, the existing pedestrian path between the two sides is long and includes steep slopes, especially on the Crest Road bridge over the tracks. Designs are underway to provide for a fully compliant pathway.",
      "severity": 1,
      "route_id": "unknown"
    },
    {
      "id": "1010951",
      "title": "",
      "description": "Affected direction: westbound\r\n\r\nAffected stations:\r\nEnglewood Avenue",
      "severity": 7,
      "route_id": "unknown"
    },
    {
      "id": "1010351",
      "title": "",
      "description": null,
      "severity": 3,
      "route_id": "unknown"
    },
    {
      "id": "1011898",
      "title": "",
      "description": "No service to Charles St South, Charles St, Beacon St or Park and Tremont Streets.\r\n\r\nConnections can be made at:\r\n285 Tremont St.\r\n\r\nAffected stops:\r\nTremont St opp Temple Pl (inbound)\r\nTremont St @ Boylston Station (outbound)\r\nCharles St S @ Park Plaza (inbound)\r\nCharles St @ Beacon St (inbound)\r\nBeacon St opp Walnut St (inbound)\r\nBeacon St @ Park St (inbound)\r\nTremont St opp Temple Pl (inbound)",
      "severity": 7,
      "route_id": "unknown"
    },
    {
      "id": "1011891",
      "title": "",
      "description": "Affected stops:\r\nN Harvard St @ Western Ave (outbound)\r\nN Harvard St opp Harvard Stadium Gate 2 (outbound)\r\nJFK St @ Eliot St (inbound)\r\nN Harvard St @ Gate 2 Harvard Stadium (inbound)\r\nN Harvard St @ S Campus Dr (inbound)",
      "severity": 1,
      "route_id": "unknown"
    },
    {
      "id": "1001864",
      "title": "",
      "description": null,
      "severity": 3,
      "route_id": "unknown"
    },
    {
      "id": "1007352",
      "title": "",
      "description": null,
      "severity": 3,
      "route_id": "unknown"
    },
    {
      "id": "1001815",
      "title": "",
      "description": null,
      "severity": 1,
      "route_id": "unknown"
    },
    {
      "id": "1001818",
      "title": "",
      "description": null,
      "severity": 1,
      "route_id": "unknown"
    },
    {
      "id": "1011411",
      "title": "",
      "description": "Affected routes:\r\nCT3\r\n8\r\n19\r\n47",
      "severity": 1,
      "route_id": "unknown"
    },
    {
      "id": "1011897",
      "title": "",
      "description": "Affected stops:\r\nTemple Pl @ Washington St (outbound)\r\nTremont St @ Boylston Station (outbound)\r\nWashington St @ Essex St (inbound)\r\nTemple Pl @ Washington St (inbound)",
      "severity": 7,
      "route_id": "unknown"
    },
    {
      "id": "1012053",
      "title": "",
      "description": null,
      "severity": 3,
      "route_id": "unknown"
    },
    {
      "id": "1011958",
      "title": "",
      "description": null,
      "severity": 3,
      "route_id": "unknown"
    },
    {
      "id": "1000003",
      "title": "",
      "description": "Scheduled to complete sometime in 2027, the Reconstruction of Foster Street includes widening and resurfacing with the addition of bicycle lanes.",
      "severity": 1,
      "route_id": "unknown"
    },
    {
      "id": "1003745",
      "title": "",
      "description": "Skipped outbound stops:\r\n136 Georgetowne Pl\r\n\r\nSkipped inbound stops:\r\n136 Georgetowne Pl",
      "severity": 7,
      "route_id": "unknown"
    },
    {
      "id": "1008495",
      "title": "",
      "description": "Skipped inbound stops:\r\nHammond St @ Plympton St",
      "severity": 7,
      "route_id": "unknown"
    },
    {
      "id": "1001820",
      "title": "",
      "description": null,
      "severity": 1,
      "route_id": "unknown"
    },
    {
      "id": "1011893",
      "title": "",
      "description": null,
      "severity": 7,
      "route_id": "unknown"
    },
    {
      "id": "1009765",
      "title": "",
      "description": "Pedestrian Access:\r\nThere will be no access between the Hingham Ferry Terminal and DCR building. Pedestrian access to and from the ferry dock will be through and around the west side of the Hingham Ferry Terminal. Some sidewalk access at the Terminal may also be restricted during this work.\r\n\r\nShipyard Drive:\r\nShipyard Drive will be closed to traffic in front of the Hingham Ferry Terminal starting at 5 AM on Thursday, May 21. Traffic will be rerouted through the Hingham Parking lot. Drop-offs and pick-ups will be relocated to the parking lot. Traffic police and signage will be in place to direct traffic. This closure should last approximately one week. ",
      "severity": 4,
      "route_id": "unknown"
    },
    {
      "id": "1000001",
      "title": "",
      "description": "Affected lines:\r\nFoxboro Event Service\r\nProvidence/Stoughton Line",
      "severity": 1,
      "route_id": "unknown"
    },
    {
      "id": "1011900",
      "title": "",
      "description": "IB Connections: Elliot St and Mt Auburn St-Charlie\u2019s Kitchen or North Harvard St after Western Ave. OB Connections: North Harvard St before Western Ave or Johnston Gate, Harvard Sq. No service to North Harvard St from Western Ave to JFK St. No service to JFK St.\r\n\r\nAffected stops:\r\nHarvard Ave @ Brighton Ave (outbound)\r\n7 Winship St (outbound)\r\nBrighton Ave opp Quint Ave (outbound)\r\nN Harvard St opp Harvard Stadium Gate 2 (outbound)\r\nWinship St @ Union St (outbound)\r\nJFK St @ Eliot St (outbound)\r\nCambridge St @ N Beacon St (outbound)\r\nWinship St @ Union St (outbound)\r\nN Harvard St @ Gate 2 Harvard Stadium (inbound)\r\nN Harvard St @ S Campus Dr (inbound)\r\nN Harvard St @ Franklin St (inbound)\r\nN Harvard St @ Coolidge Rd (inbound)",
      "severity": 1,
      "route_id": "unknown"
    },
    {
      "id": "1001859",
      "title": "",
      "description": "Affected routes:\r\n60\r\n65",
      "severity": 1,
      "route_id": "unknown"
    },
    {
      "id": "1007380",
      "title": "",
      "description": null,
      "severity": 3,
      "route_id": "unknown"
    },
    {
      "id": "1001042",
      "title": "",
      "description": null,
      "severity": 8,
      "route_id": "unknown"
    },
    {
      "id": "1009585",
      "title": "",
      "description": "Please use Back Bay Elevator 855 (Commuter Rail Track 1 & 3)",
      "severity": 1,
      "route_id": "unknown"
    },
    {
      "id": "1011894",
      "title": "",
      "description": "Affected stops:\r\nWestern Ave @ Green St (outbound)\r\nWestern Ave @ Kinnaird St (outbound)\r\nWestern Ave @ Howard St (outbound)\r\nWestern Ave @ Putnam Ave (outbound)\r\nWestern Ave opp Genzyme (outbound)\r\n125 Western Ave (outbound)\r\nWestern Ave @ N Harvard St (outbound)\r\nWestern Ave opp Riverdale St (outbound)\r\nWestern Ave @ Everett St (outbound)\r\n367 Western Ave opp Brighton Mills Mall (outbound)\r\nWestern Ave opp Litchfield St (outbound)\r\n445 Western Ave (outbound)\r\n495 Western Ave (outbound)\r\nWestern Ave @ Mackin St (inbound)\r\n450 Western Ave (inbound)\r\nGreen St @ Magazine St (inbound)\r\nWestern Ave @ Litchfield St (inbound)\r\nWestern Ave @ Everett St (inbound)\r\nWestern Ave @ Riverdale St (inbound)\r\nWestern Ave @ Travis St (inbound)\r\n130 Western Ave (inbound)\r\nWestern Ave @ Genzyme (inbound)\r\nRiver St opp Blackstone St (inbound)\r\nRiver St @ Fairmont St (inbound)\r\nRiver St @ Kelly Rd (inbound)\r\nRiver St opp Kinnaird St (inbound)\r\nRiver St @ Green St (inbound)",
      "severity": 1,
      "route_id": "unknown"
    },
    {
      "id": "1007353",
      "title": "",
      "description": null,
      "severity": 3,
      "route_id": "unknown"
    },
    {
      "id": "1002998",
      "title": "",
      "description": null,
      "severity": 3,
      "route_id": "unknown"
    },
    {
      "id": "1012059",
      "title": "",
      "description": "To exit the Red Line, use nearby South Station Elevator 918. To exit the Silver Line, take South Station Elevator 927 to the Alewife platform, then take South Station Elevator 919 to the Airport/Design Center/Chelsea platform. At the Silver Line platform, use South Station Elevator 918 to access the lobby. To board the Red Line, use South Station Elevator 918 located on the opposide side of the lobby.",
      "severity": 3,
      "route_id": "unknown"
    },
    {
      "id": "1001816",
      "title": "",
      "description": null,
      "severity": 1,
      "route_id": "unknown"
    },
    {
      "id": "1002997",
      "title": "",
      "description": null,
      "severity": 3,
      "route_id": "unknown"
    },
    {
      "id": "1002058",
      "title": "",
      "description": "Please use nearby ramp to the platform.",
      "severity": 3,
      "route_id": "unknown"
    },
    {
      "id": "1000004",
      "title": "",
      "description": "Affected lines:\r\nFall River/New Bedford Line",
      "severity": 1,
      "route_id": "unknown"
    },
    {
      "id": "1001821",
      "title": "",
      "description": null,
      "severity": 1,
      "route_id": "unknown"
    },
    {
      "id": "1008808",
      "title": "",
      "description": "Tappan Street will remain closed in the outbound direction only (toward Cleveland Circle) from June 13 through July 10.\r\n\r\nAffected stations:\r\nTappan Street",
      "severity": 7,
      "route_id": "unknown"
    },
    {
      "id": "1001863",
      "title": "",
      "description": "Skipped outbound stops:\r\nOxford St @ Washington St\r\nOxford St @ Market St",
      "severity": 7,
      "route_id": "unknown"
    },
    {
      "id": "1001817",
      "title": "",
      "description": "The escalator will remain out of service for the foreseeable future. This decision was made after a thorough inspection determined that corrosion on the escalator\u2019s steel truss was so severe that it could not be repaired further and that a complete replacement of the escalator would be required. Replacing the escalator at this location requires a more extended unit meeting modern escalator safety requirements. This longer unit will require significant alteration to the station entrance to meet code requirements. The MBTA has currently begun design work to understand what station upgrades will be needed.\r\n\r\nDue to these complexities, we expect the escalator will remain out of service for a significant time. We recognize the challenges this poses to our riders, and please know we are working to identify a solution as quickly as possible. In the meantime, Government Center Station, which is fully accessible and serves the Blue Line, is under a quarter-mile from Bowdoin Station.",
      "severity": 1,
      "route_id": "unknown"
    },
    {
      "id": "1009729",
      "title": "",
      "description": null,
      "severity": 3,
      "route_id": "unknown"
    }
  ],
  "delays_by_route": {},
  "vehicle_positions": [
    {
      "id": "y2010",
      "route_id": "110",
      "route_type": null,
      "latitude": 42.404121,
      "longitude": -71.030247,
      "bearing": 95,
      "speed": null,
      "status": null
    },
    {
      "id": "R-5489B132",
      "route_id": "Red",
      "route_type": null,
      "latitude": 42.39621,
      "longitude": -71.14054,
      "bearing": 85,
      "speed": null,
      "status": null
    },
    {
      "id": "R-5489C397",
      "route_id": "Red",
      "route_type": null,
      "latitude": 42.39618,
      "longitude": -71.14054,
      "bearing": 85,
      "speed": null,
      "status": null
    },
    {
      "id": "y1787",
      "route_id": "171",
      "route_type": null,
      "latitude": 42.349706,
      "longitude": -71.0473,
      "bearing": 125,
      "speed": null,
      "status": null
    },
    {
      "id": "y2116",
      "route_id": "109",
      "route_type": null,
      "latitude": 42.419541,
      "longitude": -71.044491,
      "bearing": 210,
      "speed": null,
      "status": null
    },
    {
      "id": "R-5489BF7D",
      "route_id": "Red",
      "route_type": null,
      "latitude": 42.20749,
      "longitude": -71.00173,
      "bearing": 10,
      "speed": null,
      "status": null
    },
    {
      "id": "ynk316",
      "route_id": "Shuttle-Generic",
      "route_type": null,
      "latitude": 42.338733,
      "longitude": -71.043971,
      "bearing": null,
      "speed": null,
      "status": null
    },
    {
      "id": "ynk225",
      "route_id": "Shuttle-Generic",
      "route_type": null,
      "latitude": 42.201464,
      "longitude": -71.064345,
      "bearing": null,
      "speed": null,
      "status": null
    },
    {
      "id": "y1851",
      "route_id": "15",
      "route_type": null,
      "latitude": 42.267852,
      "longitude": -71.092019,
      "bearing": null,
      "speed": null,
      "status": null
    },
    {
      "id": "y3148",
      "route_id": "104",
      "route_type": null,
      "latitude": 42.4148,
      "longitude": -71.048663,
      "bearing": 213,
      "speed": null,
      "status": null
    },
    {
      "id": "y1978",
      "route_id": "104",
      "route_type": null,
      "latitude": 42.38789,
      "longitude": -71.07364,
      "bearing": 315,
      "speed": null,
      "status": null
    },
    {
      "id": "ynk241",
      "route_id": "Shuttle-Generic",
      "route_type": null,
      "latitude": 42.338023,
      "longitude": -71.036766,
      "bearing": null,
      "speed": null,
      "status": null
    },
    {
      "id": "ynk223",
      "route_id": "Shuttle-Generic",
      "route_type": null,
      "latitude": 42.201414,
      "longitude": -71.064854,
      "bearing": null,
      "speed": null,
      "status": null
    },
    {
      "id": "y3111",
      "route_id": "116",
      "route_type": null,
      "latitude": 42.414363,
      "longitude": -71.009716,
      "bearing": 206,
      "speed": null,
      "status": null
    },
    {
      "id": "y2062",
      "route_id": "109",
      "route_type": null,
      "latitude": 42.394076,
      "longitude": -71.067564,
      "bearing": 29,
      "speed": null,
      "status": null
    },
    {
      "id": "y2046",
      "route_id": "104",
      "route_type": null,
      "latitude": 42.388625,
      "longitude": -71.074019,
      "bearing": 180,
      "speed": null,
      "status": null
    },
    {
      "id": "y1671",
      "route_id": "24",
      "route_type": null,
      "latitude": 42.30309,
      "longitude": -71.1102,
      "bearing": 0,
      "speed": null,
      "status": null
    },
    {
      "id": "R-5489A7EE",
      "route_id": "Red",
      "route_type": null,
      "latitude": 42.20749,
      "longitude": -71.00156,
      "bearing": 10,
      "speed": null,
      "status": null
    },
    {
      "id": "y1820",
      "route_id": "23",
      "route_type": null,
      "latitude": 42.367115,
      "longitude": -71.027818,
      "bearing": 54,
      "speed": null,
      "status": null
    },
    {
      "id": "y2022",
      "route_id": "8993",
      "route_type": null,
      "latitude": 42.399594,
      "longitude": -71.111563,
      "bearing": 272,
      "speed": null,
      "status": null
    },
    {
      "id": "y1918",
      "route_id": "28",
      "route_type": null,
      "latitude": 42.26752,
      "longitude": -71.09178,
      "bearing": 270,
      "speed": null,
      "status": null
    },
    {
      "id": "y2038",
      "route_id": "110",
      "route_type": null,
      "latitude": 42.394042,
      "longitude": -71.06756,
      "bearing": 18,
      "speed": null,
      "status": null
    },
    {
      "id": "ynk305",
      "route_id": "Shuttle-Generic",
      "route_type": null,
      "latitude": 42.338761,
      "longitude": -71.044394,
      "bearing": null,
      "speed": null,
      "status": null
    },
    {
      "id": "y1890",
      "route_id": "16",
      "route_type": null,
      "latitude": 42.3393,
      "longitude": -71.05832,
      "bearing": 270,
      "speed": null,
      "status": null
    },
    {
      "id": "ynk250",
      "route_id": "Shuttle-Generic",
      "route_type": null,
      "latitude": 42.337693,
      "longitude": -71.036335,
      "bearing": null,
      "speed": null,
      "status": null
    }
  ]
}